[
  {
    "riddleTitle":"Talking Points",
    "treasureHuntTitle":"Market Mystery",
    "next": "Advent",
    "location":{
      "latitude":37.784991,
      "longitude":-122.406624,
      "name": "Market and Fourth"
    },
    "riddleContent":"Feeling chatty.",
    "riddleAnswer":"converse"
  },
  {
    "riddleTitle":"Advent",
    "next":"Das Spiel",
    "previous": "Talking Points",
    "treasureHuntTitle":"Market Mystery",
    "location":{
      "latitude":37.784613,
      "longitude":-122.407617, 
      "name": "Powell-Market Cable Car Turntable"
    },
    "riddleContent":"Birth of a man memorialized in song.",
    "riddleAnswer":"1836"
  },
  {
    "riddleTitle":"Das Spiel",
    "previous": "Advent",
    "treasureHuntTitle":"Market Mystery",
    "location":{
      "latitude":37.783523,
      "longitude":-122.4091, 
      "name": "Mason and Turk"
    },
    "riddleContent":"Find the cellar.",
    "riddleAnswer":"mikkeller"
  }
]